laclongagent/__init__.py
laclongagent/agent/agent.py
laclongagent/examples/deepsearch.md
laclongagent/examples/todaytrend.md
laclongagent/register/tool.py
laclongagent/tools/computer_tools.py
laclongagent/tools/deepsearch.py
laclongagent/tools/hello.py
laclongagent/tools/terminal_tools.py
laclongagent/tools/trending_news.py
laclongagent/tools/websearch_tools.py
laclongagent/tools/yfinance_tools.py
laclongagent-0.1.2.dist-info/LICENSE
laclongagent-0.1.2.dist-info/METADATA
laclongagent-0.1.2.dist-info/WHEEL
laclongagent-0.1.2.dist-info/RECORD
