Metadata-Version: 2.3
Name: laclongagent
Version: 0.1.2
Summary: 
Author: phamdinhkhanh
Author-email: phamdinhkhanh.tkt53.neu@gmail.com
Requires-Python: >=3.10,<4.0
Classifier: Programming Language :: Python :: 3
Classifier: Programming Language :: Python :: 3.10
Classifier: Programming Language :: Python :: 3.11
Classifier: Programming Language :: Python :: 3.12
Classifier: Programming Language :: Python :: 3.13
Requires-Dist: googlenewsdecoder (==0.1.7)
Requires-Dist: langchain-core (==0.3.41)
Requires-Dist: langchain-openai (==0.3.7)
Requires-Dist: langchain-together (==0.3.0)
Requires-Dist: matplotlib (==3.5.3)
Requires-Dist: nbformat (==5.10.4)
Requires-Dist: numpy (>=1.26.0,<2.0.0)
Requires-Dist: pandas (>=2.2.3,<3.0.0)
Requires-Dist: plotly (==5.22.0)
Requires-Dist: python-dotenv (==1.0.0)
Requires-Dist: tavily-python (>=0.7.0,<0.8.0)
Requires-Dist: yfinance (==0.2.54)
